{
  "code": "imn",
  "iso2": "IM",
  "name": "Isle of Man / Mannin",
  "legal_model": {
    "recreational": {
      "raw_status": "UNKNOWN",
      "status": "ILLEGAL",
      "enforcement": "STRICT",
      "scope": "NONE"
    },
    "medical": {
      "raw_status": "UNKNOWN",
      "status": "ILLEGAL",
      "enforcement": "STRICT",
      "scope": "NONE",
      "override_reason": null
    },
    "distribution": {
      "status": "tolerated",
      "scopes": {
        "possession": null,
        "use": null,
        "sale": "tolerated",
        "cultivation": null,
        "import": null,
        "trafficking": null
      },
      "enforcement": "fine-based",
      "flags": [
        "sale_tolerated"
      ],
      "modifiers": [
        "but",
        "only",
        "may",
        "however"
      ]
    },
    "signals": {
      "status": "illegal",
      "final_risk": "HIGH_RISK",
      "enforcement_level": "active",
      "penalties": {
        "prison": true,
        "prison_priority": 3,
        "arrest": false,
        "fine": true,
        "severity_score": 4,
        "possession": {
          "prison": true,
          "arrest": false,
          "fine": true,
          "severe": true
        },
        "trafficking": {
          "prison": false,
          "arrest": false,
          "fine": false,
          "severe": false
        }
      },
      "confidence": "medium",
      "sources": [
        {
          "title": "Isle of Man / Mannin",
          "url": null,
          "depth": 0,
          "type": "summary"
        },
        {
          "title": "Legality of cannabis",
          "url": null,
          "depth": 1,
          "type": "traversal"
        }
      ],
      "explain": [
        "rule: raw_illegal | source: Legality of cannabis | type: traversal | priority: 3 | scope: use",
        "rule: illegal | source: Legality of cannabis | type: traversal | priority: 3 | scope: use",
        "rule: penalty_prison | source: Legality of cannabis | type: traversal | priority: 3 | scope: possession",
        "rule: penalty_fine | source: Legality of cannabis | type: traversal | priority: 3 | scope: possession",
        "rule: legal | source: Legality of cannabis | type: traversal | priority: 3 | scope: general",
        "rule: legal | source: Legality of cannabis | type: traversal | priority: 3 | scope: sale",
        "rule: legal | source: Legality of cannabis | type: traversal | priority: 3 | scope: possession",
        "rule: sale_tolerated | source: Legality of cannabis | type: traversal | priority: 3 | scope: sale",
        "rule: rec_tolerated | source: Legality of cannabis | type: traversal | priority: 3 | scope: sale",
        "rule: raw_illegal | source: Legality of cannabis | type: traversal | priority: 3 | scope: general",
        "rule: illegal | source: Legality of cannabis | type: traversal | priority: 3 | scope: general",
        "rule: penalty_prison | source: Legality of cannabis | type: traversal | priority: 3 | scope: general",
        "rule: legal | source: Legality of cannabis | type: traversal | priority: 3 | scope: use",
        "rule: medical_legal | source: Legality of cannabis | type: traversal | priority: 3 | scope: use"
      ],
      "secondary_source": {
        "has_article": true,
        "article_len": 4262,
        "source_confidence": "prison_signal",
        "signals": {
          "prison_notes": false,
          "prison_article": true,
          "enforcement_notes": null,
          "enforcement_article": null,
          "distribution_notes": null,
          "distribution_article": "illegal"
        }
      }
    },
    "enforcement_flags": [
      "fine_based"
    ],
    "applied_rules": [
      "raw_illegal",
      "penalty_prison",
      "penalty_fine",
      "sale_tolerated",
      "medical_legal"
    ],
    "notes_normalized": "Cannabis is illegal in Isle of Man / Mannin. Medical cannabis is illegal. Distribution is tolerated. Prison exposure detected."
  },
  "notes_normalized": "Cannabis is illegal in Isle of Man / Mannin. Medical cannabis is illegal. Distribution is tolerated. Prison exposure detected.",
  "notes_raw": "Main article: Legality_of_cannabis.\n\n'''Adult legal status of cannabis possession for recreational use''' 1 ----\n\n----]]\n\n'''Adult legal status of cannabis for medical use''' 1 ----",
  "facts": {
    "possession_limit": null,
    "cultivation": null,
    "penalty": null
  },
  "related_codes": [
    "gbr",
    "irl",
    "ggy"
  ],
  "related_names": [
    {
      "code": "gbr",
      "name": "United Kingdom"
    },
    {
      "code": "irl",
      "name": "Ireland / Éire"
    },
    {
      "code": "ggy",
      "name": "Guernsey / Guernesey"
    }
  ],
  "coordinates": {
    "lat": 54.220833,
    "lng": -4.530069
  },
  "sources": {
    "legal": null,
    "wiki": "https://en.wikipedia.org/wiki/Isle_of_Man",
    "wiki_truth": null,
    "citations": []
  },
  "updated_at": "2026-04-10",
  "normalized_version": "v1",
  "graph": {
    "region": "EU",
    "seo_cluster": "EU_GENERAL",
    "geo_neighbors": [
      {
        "code": "gbr",
        "name": "United Kingdom"
      },
      {
        "code": "irl",
        "name": "Ireland / Éire"
      },
      {
        "code": "ggy",
        "name": "Guernsey / Guernesey"
      }
    ],
    "legal_similarity": [
      {
        "code": "jey",
        "name": "Jersey / Jèrri"
      },
      {
        "code": "fro",
        "name": "Faroe Islands / Færøerne"
      },
      {
        "code": "fra",
        "name": "France"
      }
    ],
    "cluster_links": [
      {
        "code": "bel",
        "name": "Belgium / Belgien"
      },
      {
        "code": "nld",
        "name": "Netherlands / Nederland"
      }
    ],
    "same_country_states": [],
    "federal_parent": null
  },
  "hashes": {
    "code": "imn",
    "content_hash": "b948cfc440e4e09dc10b025b835b227fa49f0192e38a63e06e3de742b87c01ae",
    "notes_hash": "b2adb8c39e55beea2bc0bf2ecbed3fc90c4e7bd42a90bd8dd48bfa1636565576",
    "model_hash": "a697664fa8fc1eca50e248e73126f09d6f5c7679312ce0088b6c0aadea6d6335"
  },
  "geo_code": "IM",
  "node_type": "country",
  "parent_country": null,
  "state_modifiers": null
}
